Workbook

Sheet Instructions
B2: AI Agent Security Assessment Worksheet
B3: Based on ISACA, Cybersecurity Recommendations for Securing AI Agents (2026): 11 practice categories, 80 controls (Figure 3), the 15-item Secure by Default checklist (Figure 4), and the Appendix A data handling guide.
B5: ASSESSMENT SCOPE
B6: Organization
B7: Agent(s) / system in scope
B8: Agent description & autonomy level
B9: Assessor
B10: Assessment date
B11: Version / status
B13: HOW TO USE
B14: 1. Scope | C14: Complete the scope block above. Use one copy of this workbook per agent, or per group of agents sharing one runtime and toolset, because controls such as sandboxing and the PEP differ by agent.
B15: 2. Assess | C15: On the Assessment tab, set Status and Maturity for each control, then record evidence, owner, and observations. Only yellow cells are inputs; grey cells calculate.
B16: 3. Prioritize | C16: Suggested Criticality is a starting default. Adjust it to the agent's actual blast radius (a read-only summarizer vs. an agent with write access to production). Gap Priority recalculates automatically.
B17: 4. Data | C17: On the Data Handling tab, decide what each data class may do inside the agent (context, memory, logs, external provider). This is the evidence for DAT-03.
B18: 5. Review | C18: Summary rolls coverage up by practice category. Checklist rolls the 80 controls up to ISACA's 15 Secure by Default items. Filter the Assessment tab on Gap Priority = P1 to start the remediation plan.
B20: LEGEND
B21: Input cell | C21: Fill in or select from the dropdown.
B22: Calculated cell | C22: Formula; do not overwrite.
B24: STATUS & SCORING
B25: Implemented | C25: Control is in place, operating, and evidenced. Score 1.0.
B26: Partially Implemented | C26: Covers only some agents, tools, or environments, is undocumented, or has no evidence that it operates. Score 0.5.
B27: Not Implemented | C27: Control is absent. Score 0.
B28: Not Applicable | C28: Excluded from scoring. Record the justification in Gap / Observations (e.g., the agent has no persistent memory).
B29: Coverage % | C29: (Implemented + 0.5 × Partial) ÷ applicable controls assessed.
B31: MATURITY (0–5)
B32: 0 – Non-existent | C32: No control or awareness.
B33: 1 – Initial | C33: Ad hoc, person-dependent.
B34: 2 – Repeatable | C34: Performed consistently but not documented.
B35: 3 – Defined | C35: Documented, standardized, owned.
B36: 4 – Managed | C36: Measured and monitored, with metrics and review.
B37: 5 – Optimized | C37: Continuously improved; automated where possible.
B39: GAP PRIORITY LOGIC
B40: P1 | C40: High criticality and Not Implemented.
B41: P2 | C41: High criticality and Partial, or Medium criticality and Not Implemented.
B42: P3 | C42: All other gaps.
B43: (blank) | C43: Implemented, Not Applicable, or not yet assessed.
B45: EXAMPLE ROW (format guide only)
B46: Control | C46: IAM-03 — Are short-lived credentials issued with automatic rotation?
B47: Status / Maturity | C47: Partially Implemented / 2
B48: Evidence | C48: Vault dynamic secrets config (screenshot 2026-10-20); 1-hour TTL on support-agent DB credentials
B49: Owner | C49: Platform Engineering Lead
B50: Gap / Observations | C50: Ticketing integration still uses a static API key created in 2025; no rotation
B51: Remediation | C51: Move ticketing tool to OAuth client credentials with 1-hour tokens; revoke static key
B52: Target date | C52: 2026-12-15
B54: NOTES ON THIS WORKSHEET
C55: Control wording is lightly rephrased as assessment questions from ISACA Figure 3. The Secure by Default # column links each control to the Figure 4 checklist item it supports; '—' means the control supports none directly. That mapping is the worksheet author's, not ISACA's.
C56: Suggested Criticality, the maturity scale, scoring, and Gap Priority logic were added for this worksheet; ISACA does not prescribe them.
C57: The ISO/IEC 42001 Annex A, ISO/IEC 27001:2022 Annex A, and OWASP Top 10 for LLM Applications (2025) columns are indicative cross-references, not part of the ISACA paper. Validate them before using them as audit or certification evidence. '—' means there is no clean single-control fit.
C58: ISACA repeats some controls across categories (e.g., separating reasoning from execution appears in both Secure AI Development and Segmentation). They stay in place so category scores match the paper. The See Also column links the overlaps so evidence can be reused.

Sheet Assessment
A1: AI Agent Security Assessment — Controls
A2: ="Scope: "&IF(Instructions!C7="","(set on Instructions tab)",Instructions!C7)&" | Organization: "&IF(Instructions!C6="","—",Instructions!C6) -> Scope: (set on Instructions tab) | Organization: —
A4: ID | B4: Practice Category | C4: Control (assessment question) | D4: Secure by Default # | E4: Suggested Criticality | F4: Status | G4: Maturity (0–5) | H4: Score | I4: Evidence / Artifacts | J4: Owner | K4: Gap / Observations | L4: Remediation Action | M4: Gap Priority | N4: Target Date | O4: See Also | P4: ISO/IEC 42001 Annex A | Q4: ISO/IEC 27001:2022 Annex A | R4: OWASP LLM Top 10 (2025)
A5: GOV-01 | B5: Governance, Asset Inventory, and Risk Ownership | C5: Is a current inventory maintained of every AI agent and its models, tools, plugins, vector stores, memory stores, data sources, data lineage documents, and external providers? | D5: 1 | E5: High | H5: =IF(F5="Implemented",1,IF(F5="Partially Implemented",0.5,IF(F5="Not Implemented",0,""))) | M5: =IF(OR(F5="",F5="Implemented",F5="Not Applicable"),"",IF(AND(E5="High",F5="Not Implemented"),"P1",IF(OR(E5="High",AND(E5="Medium",F5="Not Implemented")),"P2","P3"))) | O5: — | P5: A.4.2, A.4.3, A.4.4 | Q5: 5.9 | R5: —
A6: GOV-02 | B6: Governance, Asset Inventory, and Risk Ownership | C6: Are trust boundaries documented across users, the agent runtime, the model provider, the orchestration layer, the tool execution layer, enterprise systems, and human approval interfaces? | D6: 2 | E6: High | H6: =IF(F6="Implemented",1,IF(F6="Partially Implemented",0.5,IF(F6="Not Implemented",0,""))) | M6: =IF(OR(F6="",F6="Implemented",F6="Not Applicable"),"",IF(AND(E6="High",F6="Not Implemented"),"P1",IF(OR(E6="High",AND(E6="Medium",F6="Not Implemented")),"P2","P3"))) | O6: SDL-02 | P6: A.6.2.3 | Q6: 8.27 | R6: LLM01, LLM06
A7: GOV-03 | B7: Governance, Asset Inventory, and Risk Ownership | C7: Is clear control ownership assigned for deployment approval, tool access scope, monitoring, incident response, and risk acceptance? | D7: 2 | E7: High | H7: =IF(F7="Implemented",1,IF(F7="Partially Implemented",0.5,IF(F7="Not Implemented",0,""))) | M7: =IF(OR(F7="",F7="Implemented",F7="Not Applicable"),"",IF(AND(E7="High",F7="Not Implemented"),"P1",IF(OR(E7="High",AND(E7="Medium",F7="Not Implemented")),"P2","P3"))) | O7: — | P7: A.3.2 | Q7: 5.2 | R7: —
A8: GOV-04 | B8: Governance, Asset Inventory, and Risk Ownership | C8: Does each agent have an established identity, acceptable use policy, prohibited actions, and clear agent goals? | D8: — | E8: High | H8: =IF(F8="Implemented",1,IF(F8="Partially Implemented",0.5,IF(F8="Not Implemented",0,""))) | M8: =IF(OR(F8="",F8="Implemented",F8="Not Applicable"),"",IF(AND(E8="High",F8="Not Implemented"),"P1",IF(OR(E8="High",AND(E8="Medium",F8="Not Implemented")),"P2","P3"))) | O8: IAM-01 | P8: A.9.2, A.9.4 | Q8: 5.10 | R8: LLM06
A9: GOV-05 | B9: Governance, Asset Inventory, and Risk Ownership | C9: Are periodic security and risk reviews required before agent capabilities are expanded? | D9: — | E9: Medium | H9: =IF(F9="Implemented",1,IF(F9="Partially Implemented",0.5,IF(F9="Not Implemented",0,""))) | M9: =IF(OR(F9="",F9="Implemented",F9="Not Applicable"),"",IF(AND(E9="High",F9="Not Implemented"),"P1",IF(OR(E9="High",AND(E9="Medium",F9="Not Implemented")),"P2","P3"))) | O9: SDL-11 | P9: A.5.2 | Q9: 5.8 | R9: LLM06
A10: GOV-06 | B10: Governance, Asset Inventory, and Risk Ownership | C10: Is agent governance aligned to enterprise security, privacy, legal, and third-party risk programs? | D10: — | E10: Medium | H10: =IF(F10="Implemented",1,IF(F10="Partially Implemented",0.5,IF(F10="Not Implemented",0,""))) | M10: =IF(OR(F10="",F10="Implemented",F10="Not Applicable"),"",IF(AND(E10="High",F10="Not Implemented"),"P1",IF(OR(E10="High",AND(E10="Medium",F10="Not Implemented")),"P2","P3"))) | O10: SUP-04 | P10: A.2.3, A.10.3 | Q10: 5.1, 5.19 | R10: —
A11: SDL-01 | B11: Secure AI Development, Change Management, and Continuous Assurance | C11: Are AI agents integrated into the secure SDLC, applying secure-by-design and privacy-by-design principles with controlled development, testing, and production release processes? | D11: 13 | E11: High | H11: =IF(F11="Implemented",1,IF(F11="Partially Implemented",0.5,IF(F11="Not Implemented",0,""))) | M11: =IF(OR(F11="",F11="Implemented",F11="Not Applicable"),"",IF(AND(E11="High",F11="Not Implemented"),"P1",IF(OR(E11="High",AND(E11="Medium",F11="Not Implemented")),"P2","P3"))) | O11: — | P11: A.6.1.3, A.6.2.5 | Q11: 8.25, 8.31 | R11: —
A12: SDL-02 | B12: Secure AI Development, Change Management, and Continuous Assurance | C12: Is each agent workflow threat-modelled, including user input, retrieval, memory, inference, tool calls, APIs, human approvals, output delivery, tenant boundaries, and privileged actions? | D12: 13 | E12: High | H12: =IF(F12="Implemented",1,IF(F12="Partially Implemented",0.5,IF(F12="Not Implemented",0,""))) | M12: =IF(OR(F12="",F12="Implemented",F12="Not Applicable"),"",IF(AND(E12="High",F12="Not Implemented"),"P1",IF(OR(E12="High",AND(E12="Medium",F12="Not Implemented")),"P2","P3"))) | O12: GOV-02 | P12: A.6.1.3, A.6.2.2 | Q12: 8.27 | R12: LLM01, LLM06
A13: SDL-03 | B13: Secure AI Development, Change Management, and Continuous Assurance | C13: Are AI-specific threats addressed: prompt injection, indirect prompt injection, data exfiltration, SSRF, memory poisoning, cross-user/cross-tenant leakage, excessive permissions, malicious tool output, model inversion, unsafe file ingestion, and compromised third parties? | D13: 13 | E13: High | H13: =IF(F13="Implemented",1,IF(F13="Partially Implemented",0.5,IF(F13="Not Implemented",0,""))) | M13: =IF(OR(F13="",F13="Implemented",F13="Not Applicable"),"",IF(AND(E13="High",F13="Not Implemented"),"P1",IF(OR(E13="High",AND(E13="Medium",F13="Not Implemented")),"P2","P3"))) | O13: PID-01 | P13: A.6.1.3 | Q13: 8.27 | R13: LLM01, LLM02, LLM04, LLM06, LLM08
A14: SDL-04 | B14: Secure AI Development, Change Management, and Continuous Assurance | C14: Are reasoning, retrieval, and action execution separated into controlled stages, with least-privilege tool access, external policy enforcement, and explicit authorization for high-impact actions? | D14: 9 | E14: High | H14: =IF(F14="Implemented",1,IF(F14="Partially Implemented",0.5,IF(F14="Not Implemented",0,""))) | M14: =IF(OR(F14="",F14="Implemented",F14="Not Applicable"),"",IF(AND(E14="High",F14="Not Implemented"),"P1",IF(OR(E14="High",AND(E14="Medium",F14="Not Implemented")),"P2","P3"))) | O14: SEG-07, POL-01 | P14: A.6.2.2 | Q14: 8.27 | R14: LLM05, LLM06
A15: SDL-05 | B15: Secure AI Development, Change Management, and Continuous Assurance | C15: Is formal change management applied to prompts, models, policy logic, tool permissions, memory configuration, retrieval pipelines, orchestration logic, external providers, and action scope? | D15: 13 | E15: High | H15: =IF(F15="Implemented",1,IF(F15="Partially Implemented",0.5,IF(F15="Not Implemented",0,""))) | M15: =IF(OR(F15="",F15="Implemented",F15="Not Applicable"),"",IF(AND(E15="High",F15="Not Implemented"),"P1",IF(OR(E15="High",AND(E15="Medium",F15="Not Implemented")),"P2","P3"))) | O15: SDL-11, SUP-03 | P15: A.6.2.5 | Q15: 8.32 | R15: —
A16: SDL-06 | B16: Secure AI Development, Change Management, and Continuous Assurance | C16: Are version control, approval history, auditability, and rollback capability maintained for prompts, policies, model versions, orchestration logic, evaluation datasets, configurations, and IaC? | D16: 13 | E16: Medium | H16: =IF(F16="Implemented",1,IF(F16="Partially Implemented",0.5,IF(F16="Not Implemented",0,""))) | M16: =IF(OR(F16="",F16="Implemented",F16="Not Applicable"),"",IF(AND(E16="High",F16="Not Implemented"),"P1",IF(OR(E16="High",AND(E16="Medium",F16="Not Implemented")),"P2","P3"))) | O16: RES-03 | P16: A.6.2.7 | Q16: 8.9, 8.32 | R16: —
A17: SDL-07 | B17: Secure AI Development, Change Management, and Continuous Assurance | C17: Is conventional security testing performed: code review, SAST, DAST, SCA, API testing, secrets scanning, dependency scanning, IaC scanning, container scanning, and cloud configuration review? | D17: 13 | E17: Medium | H17: =IF(F17="Implemented",1,IF(F17="Partially Implemented",0.5,IF(F17="Not Implemented",0,""))) | M17: =IF(OR(F17="",F17="Implemented",F17="Not Applicable"),"",IF(AND(E17="High",F17="Not Implemented"),"P1",IF(OR(E17="High",AND(E17="Medium",F17="Not Implemented")),"P2","P3"))) | O17: SUP-02 | P17: A.6.2.4 | Q17: 8.8, 8.29 | R17: LLM03
A18: SDL-08 | B18: Secure AI Development, Change Management, and Continuous Assurance | C18: Is AI-specific adversarial testing conducted for jailbreaks, prompt injection, data exfiltration, unsafe tool use, memory poisoning, cross-user leakage, SSRF, malicious document ingestion, guardrail bypass, and unauthorized actions? | D18: 14 | E18: High | H18: =IF(F18="Implemented",1,IF(F18="Partially Implemented",0.5,IF(F18="Not Implemented",0,""))) | M18: =IF(OR(F18="",F18="Implemented",F18="Not Applicable"),"",IF(AND(E18="High",F18="Not Implemented"),"P1",IF(OR(E18="High",AND(E18="Medium",F18="Not Implemented")),"P2","P3"))) | O18: — | P18: A.6.2.4 | Q18: 8.29 | R18: LLM01, LLM02, LLM06
A19: SDL-09 | B19: Secure AI Development, Change Management, and Continuous Assurance | C19: Are LLM-specific regression tests maintained for known attack patterns, policy bypasses, guardrail failures, sensitive data exposure, tool misuse, retrieval manipulation, and memory misuse? | D19: 14 | E19: Medium | H19: =IF(F19="Implemented",1,IF(F19="Partially Implemented",0.5,IF(F19="Not Implemented",0,""))) | M19: =IF(OR(F19="",F19="Implemented",F19="Not Applicable"),"",IF(AND(E19="High",F19="Not Implemented"),"P1",IF(OR(E19="High",AND(E19="Medium",F19="Not Implemented")),"P2","P3"))) | O19: SDL-08 | P19: A.6.2.4 | Q19: 8.29 | R19: LLM01, LLM08
A20: SDL-10 | B20: Secure AI Development, Change Management, and Continuous Assurance | C20: Are privacy and confidentiality controls validated, including data minimization, sensitive data filtering, output limits, differential privacy or privacy-preserving techniques (where applicable), and prevention of unauthorized disclosure? | D20: — | E20: Medium | H20: =IF(F20="Implemented",1,IF(F20="Partially Implemented",0.5,IF(F20="Not Implemented",0,""))) | M20: =IF(OR(F20="",F20="Implemented",F20="Not Applicable"),"",IF(AND(E20="High",F20="Not Implemented"),"P1",IF(OR(E20="High",AND(E20="Medium",F20="Not Implemented")),"P2","P3"))) | O20: DAT-03 | P20: A.7.2 | Q20: 5.34, 8.11, 8.12 | R20: LLM02
A21: SDL-11 | B21: Secure AI Development, Change Management, and Continuous Assurance | C21: Are risk reassessed and controls retested when models, prompts, tools, permissions, memory behaviour, retrieval sources, providers, deployment environments, or action scope change? | D21: 13 | E21: High | H21: =IF(F21="Implemented",1,IF(F21="Partially Implemented",0.5,IF(F21="Not Implemented",0,""))) | M21: =IF(OR(F21="",F21="Implemented",F21="Not Applicable"),"",IF(AND(E21="High",F21="Not Implemented"),"P1",IF(OR(E21="High",AND(E21="Medium",F21="Not Implemented")),"P2","P3"))) | O21: GOV-05 | P21: A.5.2, A.6.2.4 | Q21: 8.32 | R21: —
A22: SDL-12 | B22: Secure AI Development, Change Management, and Continuous Assurance | C22: Are deployed agents continuously monitored for anomalous behaviour, tool usage, policy violations, retrieval activity, memory access, guardrail failures, unsafe outputs, and emerging attack patterns? | D22: 11 | E22: High | H22: =IF(F22="Implemented",1,IF(F22="Partially Implemented",0.5,IF(F22="Not Implemented",0,""))) | M22: =IF(OR(F22="",F22="Implemented",F22="Not Applicable"),"",IF(AND(E22="High",F22="Not Implemented"),"P1",IF(OR(E22="High",AND(E22="Medium",F22="Not Implemented")),"P2","P3"))) | O22: MON-03 | P22: A.6.2.6 | Q22: 8.16 | R22: LLM06, LLM10
A23: SDL-13 | B23: Secure AI Development, Change Management, and Continuous Assurance | C23: Is behavioural, performance, and governance drift detection conducted to identify degradation in quality, bias, policy adherence, refusal behaviour, tool-use behaviour, and safety controls? | D23: — | E23: Medium | H23: =IF(F23="Implemented",1,IF(F23="Partially Implemented",0.5,IF(F23="Not Implemented",0,""))) | M23: =IF(OR(F23="",F23="Implemented",F23="Not Applicable"),"",IF(AND(E23="High",F23="Not Implemented"),"P1",IF(OR(E23="High",AND(E23="Medium",F23="Not Implemented")),"P2","P3"))) | O23: SUP-06 | P23: A.6.2.6 | Q23: 8.16 | R23: LLM09
A24: SDL-14 | B24: Secure AI Development, Change Management, and Continuous Assurance | C24: Is AI supply chain risk managed across models, datasets, plugins, APIs, libraries, containers, external providers, and infrastructure dependencies? | D24: 12 | E24: Medium | H24: =IF(F24="Implemented",1,IF(F24="Partially Implemented",0.5,IF(F24="Not Implemented",0,""))) | M24: =IF(OR(F24="",F24="Implemented",F24="Not Applicable"),"",IF(AND(E24="High",F24="Not Implemented"),"P1",IF(OR(E24="High",AND(E24="Medium",F24="Not Implemented")),"P2","P3"))) | O24: SUP-01 to SUP-07 | P24: A.7.5, A.10.3 | Q24: 5.19, 5.21 | R24: LLM03, LLM04
A25: SDL-15 | B25: Secure AI Development, Change Management, and Continuous Assurance | C25: Are security release gates, rollback procedures, and incident response integration established for AI-specific failures such as data leakage, prompt injection compromise, unsafe tool execution, or provider compromise? | D25: 15 | E25: Medium | H25: =IF(F25="Implemented",1,IF(F25="Partially Implemented",0.5,IF(F25="Not Implemented",0,""))) | M25: =IF(OR(F25="",F25="Implemented",F25="Not Applicable"),"",IF(AND(E25="High",F25="Not Implemented"),"P1",IF(OR(E25="High",AND(E25="Medium",F25="Not Implemented")),"P2","P3"))) | O25: MON-04, RES-03 | P25: A.6.2.5 | Q25: 5.24, 8.32 | R25: —
A26: IAM-01 | B26: Strong Identity, Authentication, and Authorization | C26: Is per-agent and per-workload identity used, with no shared accounts or long-lived tokens? | D26: 3 | E26: High | H26: =IF(F26="Implemented",1,IF(F26="Partially Implemented",0.5,IF(F26="Not Implemented",0,""))) | M26: =IF(OR(F26="",F26="Implemented",F26="Not Applicable"),"",IF(AND(E26="High",F26="Not Implemented"),"P1",IF(OR(E26="High",AND(E26="Medium",F26="Not Implemented")),"P2","P3"))) | O26: GOV-04 | P26: — | Q26: 5.16 | R26: LLM06
A27: IAM-02 | B27: Strong Identity, Authentication, and Authorization | C27: Is workload identity and federated access preferred over static credentials? | D27: 4 | E27: High | H27: =IF(F27="Implemented",1,IF(F27="Partially Implemented",0.5,IF(F27="Not Implemented",0,""))) | M27: =IF(OR(F27="",F27="Implemented",F27="Not Applicable"),"",IF(AND(E27="High",F27="Not Implemented"),"P1",IF(OR(E27="High",AND(E27="Medium",F27="Not Implemented")),"P2","P3"))) | O27: DAT-02 | P27: — | Q27: 5.16, 5.17 | R27: —
A28: IAM-03 | B28: Strong Identity, Authentication, and Authorization | C28: Are short-lived credentials issued with automatic rotation? | D28: 4 | E28: High | H28: =IF(F28="Implemented",1,IF(F28="Partially Implemented",0.5,IF(F28="Not Implemented",0,""))) | M28: =IF(OR(F28="",F28="Implemented",F28="Not Applicable"),"",IF(AND(E28="High",F28="Not Implemented"),"P1",IF(OR(E28="High",AND(E28="Medium",F28="Not Implemented")),"P2","P3"))) | O28: DAT-02 | P28: — | Q28: 5.17, 8.5 | R28: —
A29: IAM-04 | B29: Strong Identity, Authentication, and Authorization | C29: Are least-privilege controls applied to every tool, API, knowledge source, and data store the agent can access? | D29: 3 | E29: High | H29: =IF(F29="Implemented",1,IF(F29="Partially Implemented",0.5,IF(F29="Not Implemented",0,""))) | M29: =IF(OR(F29="",F29="Implemented",F29="Not Applicable"),"",IF(AND(E29="High",F29="Not Implemented"),"P1",IF(OR(E29="High",AND(E29="Medium",F29="Not Implemented")),"P2","P3"))) | O29: TAPI-01 | P29: — | Q29: 5.15, 5.18, 8.3 | R29: LLM06
A30: IAM-05 | B30: Strong Identity, Authentication, and Authorization | C30: Are RBAC/ABAC and just-in-time elevation used for sensitive functions? | D30: 3 | E30: Medium | H30: =IF(F30="Implemented",1,IF(F30="Partially Implemented",0.5,IF(F30="Not Implemented",0,""))) | M30: =IF(OR(F30="",F30="Implemented",F30="Not Applicable"),"",IF(AND(E30="High",F30="Not Implemented"),"P1",IF(OR(E30="High",AND(E30="Medium",F30="Not Implemented")),"P2","P3"))) | O30: POL-04 | P30: — | Q30: 5.15, 8.2 | R30: LLM06
A31: IAM-06 | B31: Strong Identity, Authentication, and Authorization | C31: Is MFA required for operators and administrators? | D31: — | E31: High | H31: =IF(F31="Implemented",1,IF(F31="Partially Implemented",0.5,IF(F31="Not Implemented",0,""))) | M31: =IF(OR(F31="",F31="Implemented",F31="Not Applicable"),"",IF(AND(E31="High",F31="Not Implemented"),"P1",IF(OR(E31="High",AND(E31="Medium",F31="Not Implemented")),"P2","P3"))) | O31: — | P31: — | Q31: 8.5 | R31: —
A32: IAM-07 | B32: Strong Identity, Authentication, and Authorization | C32: Are identities separated for human users and functions, the agent runtime, the tool runner, and admin/operator? | D32: 3 | E32: Medium | H32: =IF(F32="Implemented",1,IF(F32="Partially Implemented",0.5,IF(F32="Not Implemented",0,""))) | M32: =IF(OR(F32="",F32="Implemented",F32="Not Applicable"),"",IF(AND(E32="High",F32="Not Implemented"),"P1",IF(OR(E32="High",AND(E32="Medium",F32="Not Implemented")),"P2","P3"))) | O32: — | P32: — | Q32: 5.3, 5.16 | R32: LLM06
A33: IAM-08 | B33: Strong Identity, Authentication, and Authorization | C33: Are authorization checks enforced not only for tools but also for memory retrieval and context access? | D33: 8 | E33: High | H33: =IF(F33="Implemented",1,IF(F33="Partially Implemented",0.5,IF(F33="Not Implemented",0,""))) | M33: =IF(OR(F33="",F33="Implemented",F33="Not Applicable"),"",IF(AND(E33="High",F33="Not Implemented"),"P1",IF(OR(E33="High",AND(E33="Medium",F33="Not Implemented")),"P2","P3"))) | O33: DAT-07 | P33: — | Q33: 8.3 | R33: LLM02, LLM08
A34: SEG-01 | B34: Network Segmentation, Isolation, and Sandbox Execution | C34: Do tool execution, code interpretation, browser automation, and file parsing run in sandboxed environments (containers, VMs, or microVMs)? | D34: 5 | E34: High | H34: =IF(F34="Implemented",1,IF(F34="Partially Implemented",0.5,IF(F34="Not Implemented",0,""))) | M34: =IF(OR(F34="",F34="Implemented",F34="Not Applicable"),"",IF(AND(E34="High",F34="Not Implemented"),"P1",IF(OR(E34="High",AND(E34="Medium",F34="Not Implemented")),"P2","P3"))) | O34: — | P34: A.4.5 | Q34: 8.27 | R34: LLM05, LLM06
A35: SEG-02 | B35: Network Segmentation, Isolation, and Sandbox Execution | C35: Are sandboxes restricted: read-only file systems where feasible, no privileged containers, limited syscalls, ephemeral execution, and no default egress? | D35: 5 | E35: High | H35: =IF(F35="Implemented",1,IF(F35="Partially Implemented",0.5,IF(F35="Not Implemented",0,""))) | M35: =IF(OR(F35="",F35="Implemented",F35="Not Applicable"),"",IF(AND(E35="High",F35="Not Implemented"),"P1",IF(OR(E35="High",AND(E35="Medium",F35="Not Implemented")),"P2","P3"))) | O35: SEG-04 | P35: — | Q35: 8.9 | R35: LLM05
A36: SEG-03 | B36: Network Segmentation, Isolation, and Sandbox Execution | C36: Is agent infrastructure placed in segmented networks? | D36: 5 | E36: Medium | H36: =IF(F36="Implemented",1,IF(F36="Partially Implemented",0.5,IF(F36="Not Implemented",0,""))) | M36: =IF(OR(F36="",F36="Implemented",F36="Not Applicable"),"",IF(AND(E36="High",F36="Not Implemented"),"P1",IF(OR(E36="High",AND(E36="Medium",F36="Not Implemented")),"P2","P3"))) | O36: — | P36: — | Q36: 8.20, 8.22 | R36: —
A37: SEG-04 | B37: Network Segmentation, Isolation, and Sandbox Execution | C37: Is outbound traffic restricted to approved domains, APIs, and destinations? | D37: 6 | E37: High | H37: =IF(F37="Implemented",1,IF(F37="Partially Implemented",0.5,IF(F37="Not Implemented",0,""))) | M37: =IF(OR(F37="",F37="Implemented",F37="Not Applicable"),"",IF(AND(E37="High",F37="Not Implemented"),"P1",IF(OR(E37="High",AND(E37="Medium",F37="Not Implemented")),"P2","P3"))) | O37: TAPI-03 | P37: — | Q37: 8.21, 8.23 | R37: LLM02, LLM06
A38: SEG-05 | B38: Network Segmentation, Isolation, and Sandbox Execution | C38: Are outbound requests routed through inspection or proxy layers when practical? | D38: 6 | E38: Medium | H38: =IF(F38="Implemented",1,IF(F38="Partially Implemented",0.5,IF(F38="Not Implemented",0,""))) | M38: =IF(OR(F38="",F38="Implemented",F38="Not Applicable"),"",IF(AND(E38="High",F38="Not Implemented"),"P1",IF(OR(E38="High",AND(E38="Medium",F38="Not Implemented")),"P2","P3"))) | O38: MON-03 | P38: — | Q38: 8.23 | R38: LLM02
A39: SEG-06 | B39: Network Segmentation, Isolation, and Sandbox Execution | C39: Is access blocked to internal admin interfaces, metadata services, and non-approved internal network resources? | D39: 5 | E39: High | H39: =IF(F39="Implemented",1,IF(F39="Partially Implemented",0.5,IF(F39="Not Implemented",0,""))) | M39: =IF(OR(F39="",F39="Implemented",F39="Not Applicable"),"",IF(AND(E39="High",F39="Not Implemented"),"P1",IF(OR(E39="High",AND(E39="Medium",F39="Not Implemented")),"P2","P3"))) | O39: TAPI-05 | P39: — | Q39: 8.20, 8.22 | R39: LLM06
A40: SEG-07 | B40: Network Segmentation, Isolation, and Sandbox Execution | C40: Is reasoning separated from execution so the model cannot directly invoke unrestricted actions? | D40: 9 | E40: High | H40: =IF(F40="Implemented",1,IF(F40="Partially Implemented",0.5,IF(F40="Not Implemented",0,""))) | M40: =IF(OR(F40="",F40="Implemented",F40="Not Applicable"),"",IF(AND(E40="High",F40="Not Implemented"),"P1",IF(OR(E40="High",AND(E40="Medium",F40="Not Implemented")),"P2","P3"))) | O40: SDL-04, POL-01 | P40: A.6.2.2 | Q40: 8.27 | R40: LLM05, LLM06
A41: PID-01 | B41: Defense Against Prompt Injection and Untrusted Content | C41: Is all external content treated as untrusted input, including webpages, emails, PDFs, retrieved documents, user attachments, and tool outputs? | D41: 7 | E41: High | H41: =IF(F41="Implemented",1,IF(F41="Partially Implemented",0.5,IF(F41="Not Implemented",0,""))) | M41: =IF(OR(F41="",F41="Implemented",F41="Not Applicable"),"",IF(AND(E41="High",F41="Not Implemented"),"P1",IF(OR(E41="High",AND(E41="Medium",F41="Not Implemented")),"P2","P3"))) | O41: TAPI-06 | P41: — | Q41: 8.26 | R41: LLM01
A42: PID-02 | B42: Defense Against Prompt Injection and Untrusted Content | C42: Is external content prevented from overriding system or developer instructions? | D42: 7 | E42: High | H42: =IF(F42="Implemented",1,IF(F42="Partially Implemented",0.5,IF(F42="Not Implemented",0,""))) | M42: =IF(OR(F42="",F42="Implemented",F42="Not Applicable"),"",IF(AND(E42="High",F42="Not Implemented"),"P1",IF(OR(E42="High",AND(E42="Medium",F42="Not Implemented")),"P2","P3"))) | O42: — | P42: — | Q42: 8.26 | R42: LLM01, LLM07
A43: PID-03 | B43: Defense Against Prompt Injection and Untrusted Content | C43: Are content boundaries, contextual labelling, and instruction hierarchy enforcement used? | D43: 7 | E43: Medium | H43: =IF(F43="Implemented",1,IF(F43="Partially Implemented",0.5,IF(F43="Not Implemented",0,""))) | M43: =IF(OR(F43="",F43="Implemented",F43="Not Applicable"),"",IF(AND(E43="High",F43="Not Implemented"),"P1",IF(OR(E43="High",AND(E43="Medium",F43="Not Implemented")),"P2","P3"))) | O43: — | P43: — | Q43: 8.26 | R43: LLM01
... A47: PID-07 | B47: Defense Against Prompt Injection and Untrusted Content | C47: Are data provenance and source trust levels tracked so that low-trust content does not receive high action authority? | D47: 7 | E47: Medium | H47: =IF(F47="Implemented",1,IF(F47="Partially Implemented",0.5,IF(F47="Not Implemented",0,""))) | M47: =IF(OR(F47="",F47="Implemented",F47="Not Applicable"),"",IF(AND(E47="High",F47="Not Implemented"),"P1",IF(OR(E47="High",AND(E47="Medium",F47="Not Implemented")),"P2","P3"))) | O47: DAT-09 | P47: A.7.5 | Q47: 8.26 | R47: LLM01, LLM04
A48: DAT-01 | B48: Data Protection, Secrets Management, and Memory Security | C48: Are secrets never placed in prompts? | D48: — | E48: High | H48: =IF(F48="Implemented",1,IF(F48="Partially Implemented",0.5,IF(F48="Not Implemented",0,""))) | M48: =IF(OR(F48="",F48="Implemented",F48="Not Applicable"),"",IF(AND(E48="High",F48="Not Implemented"),"P1",IF(OR(E48="High",AND(E48="Medium",F48="Not Implemented")),"P2","P3"))) | O48: DAT-02 | P48: — | Q48: 5.17 | R48: LLM02, LLM07
A49: DAT-02 | B49: Data Protection, Secrets Management, and Memory Security | C49: Are a secrets manager and scoped tokens used for all credentials? | D49: 4 | E49: High | H49: =IF(F49="Implemented",1,IF(F49="Partially Implemented",0.5,IF(F49="Not Implemented",0,""))) | M49: =IF(OR(F49="",F49="Implemented",F49="Not Applicable"),"",IF(AND(E49="High",F49="Not Implemented"),"P1",IF(OR(E49="High",AND(E49="Medium",F49="Not Implemented")),"P2","P3"))) | O49: IAM-02 | P49: — | Q49: 5.17, 8.24 | R49: LLM02
A50: DAT-03 | B50: Data Protection, Secrets Management, and Memory Security | C50: Are data classification, minimization, retention limits, and encryption applied to prompts, logs, traces, memory, and outputs? (Record decisions on the Data Handling tab.) | D50: — | E50: High | H50: =IF(F50="Implemented",1,IF(F50="Partially Implemented",0.5,IF(F50="Not Implemented",0,""))) | M50: =IF(OR(F50="",F50="Implemented",F50="Not Applicable"),"",IF(AND(E50="High",F50="Not Implemented"),"P1",IF(OR(E50="High",AND(E50="Medium",F50="Not Implemented")),"P2","P3"))) | O50: SDL-10 | P50: A.7.2 | Q50: 5.12, 8.10, 8.24 | R50: LLM02
A51: DAT-04 | B51: Data Protection, Secrets Management, and Memory Security | C51: Is sensitive data redacted or tokenized in logs and observability platforms? | D51: 11 | E51: High | H51: =IF(F51="Implemented",1,IF(F51="Partially Implemented",0.5,IF(F51="Not Implemented",0,""))) | M51: =IF(OR(F51="",F51="Implemented",F51="Not Applicable"),"",IF(AND(E51="High",F51="Not Implemented"),"P1",IF(OR(E51="High",AND(E51="Medium",F51="Not Implemented")),"P2","P3"))) | O51: MON-01 | P51: — | Q51: 8.11, 8.15 | R51: LLM02
A52: DAT-05 | B52: Data Protection, Secrets Management, and Memory Security | C52: Are memory and context isolated by tenant, user, and use case? | D52: 8 | E52: High | H52: =IF(F52="Implemented",1,IF(F52="Partially Implemented",0.5,IF(F52="Not Implemented",0,""))) | M52: =IF(OR(F52="",F52="Implemented",F52="Not Applicable"),"",IF(AND(E52="High",F52="Not Implemented"),"P1",IF(OR(E52="High",AND(E52="Medium",F52="Not Implemented")),"P2","P3"))) | O52: DAT-08 | P52: — | Q52: 8.3 | R52: LLM02, LLM08
A53: DAT-06 | B53: Data Protection, Secrets Management, and Memory Security | C53: Are retention limits and time-to-live (TTL) values applied to persistent memory? | D53: 8 | E53: Medium | H53: =IF(F53="Implemented",1,IF(F53="Partially Implemented",0.5,IF(F53="Not Implemented",0,""))) | M53: =IF(OR(F53="",F53="Implemented",F53="Not Applicable"),"",IF(AND(E53="High",F53="Not Implemented"),"P1",IF(OR(E53="High",AND(E53="Medium",F53="Not Implemented")),"P2","P3"))) | O53: — | P53: — | Q53: 8.10 | R53: LLM02
A54: DAT-07 | B54: Data Protection, Secrets Management, and Memory Security | C54: Are authorization checks required before an agent can retrieve stored memory or prior interactions? | D54: 8 | E54: High | H54: =IF(F54="Implemented",1,IF(F54="Partially Implemented",0.5,IF(F54="Not Implemented",0,""))) | M54: =IF(OR(F54="",F54="Implemented",F54="Not Applicable"),"",IF(AND(E54="High",F54="Not Implemented"),"P1",IF(OR(E54="High",AND(E54="Medium",F54="Not Implemented")),"P2","P3"))) | O54: IAM-08 | P54: — | Q54: 8.3 | R54: LLM02, LLM08
A55: DAT-08 | B55: Data Protection, Secrets Management, and Memory Security | C55: Is cross-session and cross-tenant leakage prevented? | D55: 8 | E55: High | H55: =IF(F55="Implemented",1,IF(F55="Partially Implemented",0.5,IF(F55="Not Implemented",0,""))) | M55: =IF(OR(F55="",F55="Implemented",F55="Not Applicable"),"",IF(AND(E55="High",F55="Not Implemented"),"P1",IF(OR(E55="High",AND(E55="Medium",F55="Not Implemented")),"P2","P3"))) | O55: SDL-08 | P55: — | Q55: 8.3, 8.29 | R55: LLM02, LLM08
A56: DAT-09 | B56: Data Protection, Secrets Management, and Memory Security | C56: Are the provenance and integrity of stored memory and retrieved context validated to reduce poisoning risk? | D56: 7 | E56: Medium | H56: =IF(F56="Implemented",1,IF(F56="Partially Implemented",0.5,IF(F56="Not Implemented",0,""))) | M56: =IF(OR(F56="",F56="Implemented",F56="Not Applicable"),"",IF(AND(E56="High",F56="Not Implemented"),"P1",IF(OR(E56="High",AND(E56="Medium",F56="Not Implemented")),"P2","P3"))) | O56: PID-07 | P56: A.7.5 | Q56: — | R56: LLM04, LLM08
A57: TAPI-01 | B57: Secure Tool and API Integrations | C57: Are agent-accessible tools placed behind an API gateway, action broker, or policy enforcement layer? | D57: 9 | E57: High | H57: =IF(F57="Implemented",1,IF(F57="Partially Implemented",0.5,IF(F57="Not Implemented",0,""))) | M57: =IF(OR(F57="",F57="Implemented",F57="Not Applicable"),"",IF(AND(E57="High",F57="Not Implemented"),"P1",IF(OR(E57="High",AND(E57="Medium",F57="Not Implemented")),"P2","P3"))) | O57: POL-01 | P57: — | Q57: 8.26 | R57: LLM06
A58: TAPI-02 | B58: Secure Tool and API Integrations | C58: Are requests validated with authentication, authorization, schema enforcement, parameter constraints, quotas, and rate limits? | D58: 9 | E58: High | H58: =IF(F58="Implemented",1,IF(F58="Partially Implemented",0.5,IF(F58="Not Implemented",0,""))) | M58: =IF(OR(F58="",F58="Implemented",F58="Not Applicable"),"",IF(AND(E58="High",F58="Not Implemented"),"P1",IF(OR(E58="High",AND(E58="Medium",F58="Not Implemented")),"P2","P3"))) | O58: RES-01 | P58: — | Q58: 8.5, 8.26 | R58: LLM05, LLM10
A59: TAPI-03 | B59: Secure Tool and API Integrations | C59: Are explicit allowlists used for domains, endpoints, commands, repositories, and file paths? | D59: 6 | E59: High | H59: =IF(F59="Implemented",1,IF(F59="Partially Implemented",0.5,IF(F59="Not Implemented",0,""))) | M59: =IF(OR(F59="",F59="Implemented",F59="Not Applicable"),"",IF(AND(E59="High",F59="Not Implemented"),"P1",IF(OR(E59="High",AND(E59="Medium",F59="Not Implemented")),"P2","P3"))) | O59: SEG-04 | P59: — | Q59: 8.3, 8.23 | R59: LLM06
A60: TAPI-04 | B60: Secure Tool and API Integrations | C60: Are dangerous primitives blocked, such as arbitrary shell access, unrestricted file reads, and unrestricted URL fetches? | D60: 9 | E60: High | H60: =IF(F60="Implemented",1,IF(F60="Partially Implemented",0.5,IF(F60="Not Implemented",0,""))) | M60: =IF(OR(F60="",F60="Implemented",F60="Not Applicable"),"",IF(AND(E60="High",F60="Not Implemented"),"P1",IF(OR(E60="High",AND(E60="Medium",F60="Not Implemented")),"P2","P3"))) | O60: SEG-02 | P60: — | Q60: 8.27 | R60: LLM06
A61: TAPI-05 | B61: Secure Tool and API Integrations | C61: Is there protection against SSRF, internal reconnaissance, and unintended access to cloud metadata services? | D61: 6 | E61: High | H61: =IF(F61="Implemented",1,IF(F61="Partially Implemented",0.5,IF(F61="Not Implemented",0,""))) | M61: =IF(OR(F61="",F61="Implemented",F61="Not Applicable"),"",IF(AND(E61="High",F61="Not Implemented"),"P1",IF(OR(E61="High",AND(E61="Medium",F61="Not Implemented")),"P2","P3"))) | O61: SEG-06 | P61: — | Q61: 8.20, 8.26 | R61: LLM06
A62: TAPI-06 | B62: Secure Tool and API Integrations | C62: Are outputs from tools validated before being used as context for later decisions? | D62: 7 | E62: High | H62: =IF(F62="Implemented",1,IF(F62="Partially Implemented",0.5,IF(F62="Not Implemented",0,""))) | M62: =IF(OR(F62="",F62="Implemented",F62="Not Applicable"),"",IF(AND(E62="High",F62="Not Implemented"),"P1",IF(OR(E62="High",AND(E62="Medium",F62="Not Implemented")),"P2","P3"))) | O62: PID-01 | P62: — | Q62: 8.26 | R62: LLM05
... A71: MON-03 | B71: Logging, Monitoring, Detection, and Incident Response | C71: Is there monitoring for unusual tool use, excessive data retrieval, repeated bypass attempts, anomalous outbound traffic, sudden changes in model behaviour, and abuse patterns? | D71: 11 | E71: High | H71: =IF(F71="Implemented",1,IF(F71="Partially Implemented",0.5,IF(F71="Not Implemented",0,""))) | M71: =IF(OR(F71="",F71="Implemented",F71="Not Applicable"),"",IF(AND(E71="High",F71="Not Implemented"),"P1",IF(OR(E71="High",AND(E71="Medium",F71="Not Implemented")),"P2","P3"))) | O71: SDL-12 | P71: A.6.2.6 | Q71: 8.16 | R71: LLM01, LLM06, LLM10
A72: MON-04 | B72: Logging, Monitoring, Detection, and Incident Response | C72: Are agent-specific incident response playbooks in place (prompt injection, tool compromise, model/provider compromise, data leakage, cross-tenant exposure, memory poisoning)? | D72: — | E72: High | H72: =IF(F72="Implemented",1,IF(F72="Partially Implemented",0.5,IF(F72="Not Implemented",0,""))) | M72: =IF(OR(F72="",F72="Implemented",F72="Not Applicable"),"",IF(AND(E72="High",F72="Not Implemented"),"P1",IF(OR(E72="High",AND(E72="Medium",F72="Not Implemented")),"P2","P3"))) | O72: SDL-15 | P72: A.8.4 | Q72: 5.24, 5.26 | R72: —
A73: MON-05 | B73: Logging, Monitoring, Detection, and Incident Response | C73: Are escalation paths and containment procedures defined, including disabling tools or shifting the agent to read-only mode? | D73: 15 | E73: High | H73: =IF(F73="Implemented",1,IF(F73="Partially Implemented",0.5,IF(F73="Not Implemented",0,""))) | M73: =IF(OR(F73="",F73="Implemented",F73="Not Applicable"),"",IF(AND(E73="High",F73="Not Implemented"),"P1",IF(OR(E73="High",AND(E73="Medium",F73="Not Implemented")),"P2","P3"))) | O73: RES-02 | P73: — | Q73: 5.24, 5.26 | R73: —
A74: SUP-01 | B74: Model, Provider, and Software Supply Chain Security | C74: Are versions of models, model endpoints, embeddings, frameworks, plugins, and dependencies pinned and verified? | D74: 12 | E74: High | H74: =IF(F74="Implemented",1,IF(F74="Partially Implemented",0.5,IF(F74="Not Implemented",0,""))) | M74: =IF(OR(F74="",F74="Implemented",F74="Not Applicable"),"",IF(AND(E74="High",F74="Not Implemented"),"P1",IF(OR(E74="High",AND(E74="Medium",F74="Not Implemented")),"P2","P3"))) | O74: — | P74: — | Q74: 8.19, 8.32 | R74: LLM03
A75: SUP-02 | B75: Model, Provider, and Software Supply Chain Security | C75: Are SBOM, AI-BOM, dependency scanning, artifact signing, and provenance validation used? | D75: 12 | E75: Medium | H75: =IF(F75="Implemented",1,IF(F75="Partially Implemented",0.5,IF(F75="Not Implemented",0,""))) | M75: =IF(OR(F75="",F75="Implemented",F75="Not Applicable"),"",IF(AND(E75="High",F75="Not Implemented"),"P1",IF(OR(E75="High",AND(E75="Medium",F75="Not Implemented")),"P2","P3"))) | O75: SDL-07 | P75: A.7.5 | Q75: 8.8 | R75: LLM03, LLM04
A76: SUP-03 | B76: Model, Provider, and Software Supply Chain Security | C76: Is the ability to publish or update tools, prompts, agent policies, and integrations restricted? | D76: 13 | E76: High | H76: =IF(F76="Implemented",1,IF(F76="Partially Implemented",0.5,IF(F76="Not Implemented",0,""))) | M76: =IF(OR(F76="",F76="Implemented",F76="Not Applicable"),"",IF(AND(E76="High",F76="Not Implemented"),"P1",IF(OR(E76="High",AND(E76="Medium",F76="Not Implemented")),"P2","P3"))) | O76: SDL-05 | P76: — | Q76: 8.4, 8.32 | R76: LLM03, LLM07
A77: SUP-04 | B77: Model, Provider, and Software Supply Chain Security | C77: Are third-party model and tool providers vetted through supplier risk assessment? | D77: — | E77: Medium | H77: =IF(F77="Implemented",1,IF(F77="Partially Implemented",0.5,IF(F77="Not Implemented",0,""))) | M77: =IF(OR(F77="",F77="Implemented",F77="Not Applicable"),"",IF(AND(E77="High",F77="Not Implemented"),"P1",IF(OR(E77="High",AND(E77="Medium",F77="Not Implemented")),"P2","P3"))) | O77: GOV-06 | P77: A.10.3 | Q77: 5.19, 5.21 | R77: LLM03
A78: SUP-05 | B78: Model, Provider, and Software Supply Chain Security | C78: Are security-related obligations contractually defined, such as data handling, retention, model training use, security controls, residency, and breach notification? | D78: — | E78: High | H78: =IF(F78="Implemented",1,IF(F78="Partially Implemented",0.5,IF(F78="Not Implemented",0,""))) | M78: =IF(OR(F78="",F78="Implemented",F78="Not Applicable"),"",IF(AND(E78="High",F78="Not Implemented"),"P1",IF(OR(E78="High",AND(E78="Medium",F78="Not Implemented")),"P2","P3"))) | O78: — | P78: A.10.2, A.10.3 | Q78: 5.20, 5.23 | R78: LLM02, LLM03
A79: SUP-06 | B79: Model, Provider, and Software Supply Chain Security | C79: Is there monitoring for provider-side changes, behaviour drift, or endpoint spoofing? | D79: — | E79: Medium | H79: =IF(F79="Implemented",1,IF(F79="Partially Implemented",0.5,IF(F79="Not Implemented",0,""))) | M79: =IF(OR(F79="",F79="Implemented",F79="Not Applicable"),"",IF(AND(E79="High",F79="Not Implemented"),"P1",IF(OR(E79="High",AND(E79="Medium",F79="Not Implemented")),"P2","P3"))) | O79: SDL-13 | P79: A.10.3 | Q79: 5.22 | R79: LLM03, LLM09
A80: SUP-07 | B80: Model, Provider, and Software Supply Chain Security | C80: Is rollback capability maintained for model or tool changes? | D80: 15 | E80: Medium | H80: =IF(F80="Implemented",1,IF(F80="Partially Implemented",0.5,IF(F80="Not Implemented",0,""))) | M80: =IF(OR(F80="",F80="Implemented",F80="Not Applicable"),"",IF(AND(E80="High",F80="Not Implemented"),"P1",IF(OR(E80="High",AND(E80="Medium",F80="Not Implemented")),"P2","P3"))) | O80: RES-03 | P80: — | Q80: 8.32 | R80: —
A81: RES-01 | B81: Reliability, Resilience, Kill Switches, and Safe Degradation | C81: Are rate limits, quotas, token budgets, conversation limits, timeouts, retries with caps, and circuit breakers implemented? | D81: — | E81: Medium | H81: =IF(F81="Implemented",1,IF(F81="Partially Implemented",0.5,IF(F81="Not Implemented",0,""))) | M81: =IF(OR(F81="",F81="Implemented",F81="Not Applicable"),"",IF(AND(E81="High",F81="Not Implemented"),"P1",IF(OR(E81="High",AND(E81="Medium",F81="Not Implemented")),"P2","P3"))) | O81: TAPI-02 | P81: — | Q81: 8.6 | R81: LLM10
A82: RES-02 | B82: Reliability, Resilience, Kill Switches, and Safe Degradation | C82: Are global and per-capability kill switches in place to disable unsafe agent behaviour quickly? | D82: 15 | E82: High | H82: =IF(F82="Implemented",1,IF(F82="Partially Implemented",0.5,IF(F82="Not Implemented",0,""))) | M82: =IF(OR(F82="",F82="Implemented",F82="Not Applicable"),"",IF(AND(E82="High",F82="Not Implemented"),"P1",IF(OR(E82="High",AND(E82="Medium",F82="Not Implemented")),"P2","P3"))) | O82: MON-05 | P82: — | Q82: — | R82: LLM06
A83: RES-03 | B83: Reliability, Resilience, Kill Switches, and Safe Degradation | C83: Is rollback of model versions, prompts, policies, tool permissions, and dependencies supported? | D83: 15 | E83: High | H83: =IF(F83="Implemented",1,IF(F83="Partially Implemented",0.5,IF(F83="Not Implemented",0,""))) | M83: =IF(OR(F83="",F83="Implemented",F83="Not Applicable"),"",IF(AND(E83="High",F83="Not Implemented"),"P1",IF(OR(E83="High",AND(E83="Medium",F83="Not Implemented")),"P2","P3"))) | O83: SDL-06, SUP-07 | P83: — | Q83: 8.32 | R83: —
A84: RES-04 | B84: Reliability, Resilience, Kill Switches, and Safe Degradation | C84: Are safe fallback modes designed (read-only, recommendation-only, manual approval), and can critical workflows revert to manual operation if the agent is disabled? | D84: 15 | E84: High | H84: =IF(F84="Implemented",1,IF(F84="Partially Implemented",0.5,IF(F84="Not Implemented",0,""))) | M84: =IF(OR(F84="",F84="Implemented",F84="Not Applicable"),"",IF(AND(E84="High",F84="Not Implemented"),"P1",IF(OR(E84="High",AND(E84="Medium",F84="Not Implemented")),"P2","P3"))) | O84: POL-06 | P84: — | Q84: 5.29, 5.30 | R84: —

Sheet Summary
A1: Summary by Practice Category
A2: ="Scope: "&IF(Instructions!C7="","(set on Instructions tab)",Instructions!C7) -> Scope: (set on Instructions tab)
A4: Practice Category | B4: Controls | C4: Assessed | D4: Implemented | E4: Partial | F4: Not Implemented | G4: Not Applicable | H4: Not Yet Assessed | I4: Coverage % | J4: Avg Maturity | K4: Open P1 | L4: Open P2
A5: Governance, Asset Inventory, and Risk Ownership | B5: =COUNTIF(Assessment!$B$5:$B$84,$A5) -> 6 | C5: =COUNTIFS(Assessment!$B$5:$B$84,$A5,Assessment!$F$5:$F$84,"<>") -> 0 | D5: =COUNTIFS(Assessment!$B$5:$B$84,$A5,Assessment!$F$5:$F$84,"Implemented") -> 0 | E5: =COUNTIFS(Assessment!$B$5:$B$84,$A5,Assessment!$F$5:$F$84,"Partially Implemented") -> 0 | F5: =COUNTIFS(Assessment!$B$5:$B$84,$A5,Assessment!$F$5:$F$84,"Not Implemented") -> 0 | G5: =COUNTIFS(Assessment!$B$5:$B$84,$A5,Assessment!$F$5:$F$84,"Not Applicable") -> 0 | H5: =B5-C5 -> 6 | I5: =IF((D5+E5+F5)=0,"",(D5+0.5*E5)/(D5+E5+F5)) | J5: =IFERROR(AVERAGEIFS(Assessment!$G$5:$G$84,Assessment!$B$5:$B$84,$A5),"") | K5: =COUNTIFS(Assessment!$B$5:$B$84,$A5,Assessment!$M$5:$M$84,"P1") -> 0 | L5: =COUNTIFS(Assessment!$B$5:$B$84,$A5,Assessment!$M$5:$M$84,"P2") -> 0
A6: Secure AI Development, Change Management, and Continuous Assurance | B6: =COUNTIF(Assessment!$B$5:$B$84,$A6) -> 15 | C6: =COUNTIFS(Assessment!$B$5:$B$84,$A6,Assessment!$F$5:$F$84,"<>") -> 0 | D6: =COUNTIFS(Assessment!$B$5:$B$84,$A6,Assessment!$F$5:$F$84,"Implemented") -> 0 | E6: =COUNTIFS(Assessment!$B$5:$B$84,$A6,Assessment!$F$5:$F$84,"Partially Implemented") -> 0 | F6: =COUNTIFS(Assessment!$B$5:$B$84,$A6,Assessment!$F$5:$F$84,"Not Implemented") -> 0 | G6: =COUNTIFS(Assessment!$B$5:$B$84,$A6,Assessment!$F$5:$F$84,"Not Applicable") -> 0 | H6: =B6-C6 -> 15 | I6: =IF((D6+E6+F6)=0,"",(D6+0.5*E6)/(D6+E6+F6)) | J6: =IFERROR(AVERAGEIFS(Assessment!$G$5:$G$84,Assessment!$B$5:$B$84,$A6),"") | K6: =COUNTIFS(Assessment!$B$5:$B$84,$A6,Assessment!$M$5:$M$84,"P1") -> 0 | L6: =COUNTIFS(Assessment!$B$5:$B$84,$A6,Assessment!$M$5:$M$84,"P2") -> 0
A7: Strong Identity, Authentication, and Authorization | B7: =COUNTIF(Assessment!$B$5:$B$84,$A7) -> 8 | C7: =COUNTIFS(Assessment!$B$5:$B$84,$A7,Assessment!$F$5:$F$84,"<>") -> 0 | D7: =COUNTIFS(Assessment!$B$5:$B$84,$A7,Assessment!$F$5:$F$84,"Implemented") -> 0 | E7: =COUNTIFS(Assessment!$B$5:$B$84,$A7,Assessment!$F$5:$F$84,"Partially Implemented") -> 0 | F7: =COUNTIFS(Assessment!$B$5:$B$84,$A7,Assessment!$F$5:$F$84,"Not Implemented") -> 0 | G7: =COUNTIFS(Assessment!$B$5:$B$84,$A7,Assessment!$F$5:$F$84,"Not Applicable") -> 0 | H7: =B7-C7 -> 8 | I7: =IF((D7+E7+F7)=0,"",(D7+0.5*E7)/(D7+E7+F7)) | J7: =IFERROR(AVERAGEIFS(Assessment!$G$5:$G$84,Assessment!$B$5:$B$84,$A7),"") | K7: =COUNTIFS(Assessment!$B$5:$B$84,$A7,Assessment!$M$5:$M$84,"P1") -> 0 | L7: =COUNTIFS(Assessment!$B$5:$B$84,$A7,Assessment!$M$5:$M$84,"P2") -> 0
A8: Network Segmentation, Isolation, and Sandbox Execution | B8: =COUNTIF(Assessment!$B$5:$B$84,$A8) -> 7 | C8: =COUNTIFS(Assessment!$B$5:$B$84,$A8,Assessment!$F$5:$F$84,"<>") -> 0 | D8: =COUNTIFS(Assessment!$B$5:$B$84,$A8,Assessment!$F$5:$F$84,"Implemented") -> 0 | E8: =COUNTIFS(Assessment!$B$5:$B$84,$A8,Assessment!$F$5:$F$84,"Partially Implemented") -> 0 | F8: =COUNTIFS(Assessment!$B$5:$B$84,$A8,Assessment!$F$5:$F$84,"Not Implemented") -> 0 | G8: =COUNTIFS(Assessment!$B$5:$B$84,$A8,Assessment!$F$5:$F$84,"Not Applicable") -> 0 | H8: =B8-C8 -> 7 | I8: =IF((D8+E8+F8)=0,"",(D8+0.5*E8)/(D8+E8+F8)) | J8: =IFERROR(AVERAGEIFS(Assessment!$G$5:$G$84,Assessment!$B$5:$B$84,$A8),"") | K8: =COUNTIFS(Assessment!$B$5:$B$84,$A8,Assessment!$M$5:$M$84,"P1") -> 0 | L8: =COUNTIFS(Assessment!$B$5:$B$84,$A8,Assessment!$M$5:$M$84,"P2") -> 0
A9: Defense Against Prompt Injection and Untrusted Content | B9: =COUNTIF(Assessment!$B$5:$B$84,$A9) -> 7 | C9: =COUNTIFS(Assessment!$B$5:$B$84,$A9,Assessment!$F$5:$F$84,"<>") -> 0 | D9: =COUNTIFS(Assessment!$B$5:$B$84,$A9,Assessment!$F$5:$F$84,"Implemented") -> 0 | E9: =COUNTIFS(Assessment!$B$5:$B$84,$A9,Assessment!$F$5:$F$84,"Partially Implemented") -> 0 | F9: =COUNTIFS(Assessment!$B$5:$B$84,$A9,Assessment!$F$5:$F$84,"Not Implemented") -> 0 | G9: =COUNTIFS(Assessment!$B$5:$B$84,$A9,Assessment!$F$5:$F$84,"Not Applicable") -> 0 | H9: =B9-C9 -> 7 | I9: =IF((D9+E9+F9)=0,"",(D9+0.5*E9)/(D9+E9+F9)) | J9: =IFERROR(AVERAGEIFS(Assessment!$G$5:$G$84,Assessment!$B$5:$B$84,$A9),"") | K9: =COUNTIFS(Assessment!$B$5:$B$84,$A9,Assessment!$M$5:$M$84,"P1") -> 0 | L9: =COUNTIFS(Assessment!$B$5:$B$84,$A9,Assessment!$M$5:$M$84,"P2") -> 0
A10: Data Protection, Secrets Management, and Memory Security | B10: =COUNTIF(Assessment!$B$5:$B$84,$A10) -> 9 | C10: =COUNTIFS(Assessment!$B$5:$B$84,$A10,Assessment!$F$5:$F$84,"<>") -> 0 | D10: =COUNTIFS(Assessment!$B$5:$B$84,$A10,Assessment!$F$5:$F$84,"Implemented") -> 0 | E10: =COUNTIFS(Assessment!$B$5:$B$84,$A10,Assessment!$F$5:$F$84,"Partially Implemented") -> 0 | F10: =COUNTIFS(Assessment!$B$5:$B$84,$A10,Assessment!$F$5:$F$84,"Not Implemented") -> 0 | G10: =COUNTIFS(Assessment!$B$5:$B$84,$A10,Assessment!$F$5:$F$84,"Not Applicable") -> 0 | H10: =B10-C10 -> 9 | I10: =IF((D10+E10+F10)=0,"",(D10+0.5*E10)/(D10+E10+F10)) | J10: =IFERROR(AVERAGEIFS(Assessment!$G$5:$G$84,Assessment!$B$5:$B$84,$A10),"") | K10: =COUNTIFS(Assessment!$B$5:$B$84,$A10,Assessment!$M$5:$M$84,"P1") -> 0 | L10: =COUNTIFS(Assessment!$B$5:$B$84,$A10,Assessment!$M$5:$M$84,"P2") -> 0
A11: Secure Tool and API Integrations | B11: =COUNTIF(Assessment!$B$5:$B$84,$A11) -> 6 | C11: =COUNTIFS(Assessment!$B$5:$B$84,$A11,Assessment!$F$5:$F$84,"<>") -> 0 | D11: =COUNTIFS(Assessment!$B$5:$B$84,$A11,Assessment!$F$5:$F$84,"Implemented") -> 0 | E11: =COUNTIFS(Assessment!$B$5:$B$84,$A11,Assessment!$F$5:$F$84,"Partially Implemented") -> 0 | F11: =COUNTIFS(Assessment!$B$5:$B$84,$A11,Assessment!$F$5:$F$84,"Not Implemented") -> 0 | G11: =COUNTIFS(Assessment!$B$5:$B$84,$A11,Assessment!$F$5:$F$84,"Not Applicable") -> 0 | H11: =B11-C11 -> 6 | I11: =IF((D11+E11+F11)=0,"",(D11+0.5*E11)/(D11+E11+F11)) | J11: =IFERROR(AVERAGEIFS(Assessment!$G$5:$G$84,Assessment!$B$5:$B$84,$A11),"") | K11: =COUNTIFS(Assessment!$B$5:$B$84,$A11,Assessment!$M$5:$M$84,"P1") -> 0 | L11: =COUNTIFS(Assessment!$B$5:$B$84,$A11,Assessment!$M$5:$M$84,"P2") -> 0
A12: Policy Enforcement, Output Control, and Human Oversight | B12: =COUNTIF(Assessment!$B$5:$B$84,$A12) -> 6 | C12: =COUNTIFS(Assessment!$B$5:$B$84,$A12,Assessment!$F$5:$F$84,"<>") -> 0 | D12: =COUNTIFS(Assessment!$B$5:$B$84,$A12,Assessment!$F$5:$F$84,"Implemented") -> 0 | E12: =COUNTIFS(Assessment!$B$5:$B$84,$A12,Assessment!$F$5:$F$84,"Partially Implemented") -> 0 | F12: =COUNTIFS(Assessment!$B$5:$B$84,$A12,Assessment!$F$5:$F$84,"Not Implemented") -> 0 | G12: =COUNTIFS(Assessment!$B$5:$B$84,$A12,Assessment!$F$5:$F$84,"Not Applicable") -> 0 | H12: =B12-C12 -> 6 | I12: =IF((D12+E12+F12)=0,"",(D12+0.5*E12)/(D12+E12+F12)) | J12: =IFERROR(AVERAGEIFS(Assessment!$G$5:$G$84,Assessment!$B$5:$B$84,$A12),"") | K12: =COUNTIFS(Assessment!$B$5:$B$84,$A12,Assessment!$M$5:$M$84,"P1") -> 0 | L12: =COUNTIFS(Assessment!$B$5:$B$84,$A12,Assessment!$M$5:$M$84,"P2") -> 0
A13: Logging, Monitoring, Detection, and Incident Response | B13: =COUNTIF(Assessment!$B$5:$B$84,$A13) -> 5 | C13: =COUNTIFS(Assessment!$B$5:$B$84,$A13,Assessment!$F$5:$F$84,"<>") -> 0 | D13: =COUNTIFS(Assessment!$B$5:$B$84,$A13,Assessment!$F$5:$F$84,"Implemented") -> 0 | E13: =COUNTIFS(Assessment!$B$5:$B$84,$A13,Assessment!$F$5:$F$84,"Partially Implemented") -> 0 | F13: =COUNTIFS(Assessment!$B$5:$B$84,$A13,Assessment!$F$5:$F$84,"Not Implemented") -> 0 | G13: =COUNTIFS(Assessment!$B$5:$B$84,$A13,Assessment!$F$5:$F$84,"Not Applicable") -> 0 | H13: =B13-C13 -> 5 | I13: =IF((D13+E13+F13)=0,"",(D13+0.5*E13)/(D13+E13+F13)) | J13: =IFERROR(AVERAGEIFS(Assessment!$G$5:$G$84,Assessment!$B$5:$B$84,$A13),"") | K13: =COUNTIFS(Assessment!$B$5:$B$84,$A13,Assessment!$M$5:$M$84,"P1") -> 0 | L13: =COUNTIFS(Assessment!$B$5:$B$84,$A13,Assessment!$M$5:$M$84,"P2") -> 0
A14: Model, Provider, and Software Supply Chain Security | B14: =COUNTIF(Assessment!$B$5:$B$84,$A14) -> 7 | C14: =COUNTIFS(Assessment!$B$5:$B$84,$A14,Assessment!$F$5:$F$84,"<>") -> 0 | D14: =COUNTIFS(Assessment!$B$5:$B$84,$A14,Assessment!$F$5:$F$84,"Implemented") -> 0 | E14: =COUNTIFS(Assessment!$B$5:$B$84,$A14,Assessment!$F$5:$F$84,"Partially Implemented") -> 0 | F14: =COUNTIFS(Assessment!$B$5:$B$84,$A14,Assessment!$F$5:$F$84,"Not Implemented") -> 0 | G14: =COUNTIFS(Assessment!$B$5:$B$84,$A14,Assessment!$F$5:$F$84,"Not Applicable") -> 0 | H14: =B14-C14 -> 7 | I14: =IF((D14+E14+F14)=0,"",(D14+0.5*E14)/(D14+E14+F14)) | J14: =IFERROR(AVERAGEIFS(Assessment!$G$5:$G$84,Assessment!$B$5:$B$84,$A14),"") | K14: =COUNTIFS(Assessment!$B$5:$B$84,$A14,Assessment!$M$5:$M$84,"P1") -> 0 | L14: =COUNTIFS(Assessment!$B$5:$B$84,$A14,Assessment!$M$5:$M$84,"P2") -> 0
A15: Reliability, Resilience, Kill Switches, and Safe Degradation | B15: =COUNTIF(Assessment!$B$5:$B$84,$A15) -> 4 | C15: =COUNTIFS(Assessment!$B$5:$B$84,$A15,Assessment!$F$5:$F$84,"<>") -> 0 | D15: =COUNTIFS(Assessment!$B$5:$B$84,$A15,Assessment!$F$5:$F$84,"Implemented") -> 0 | E15: =COUNTIFS(Assessment!$B$5:$B$84,$A15,Assessment!$F$5:$F$84,"Partially Implemented") -> 0 | F15: =COUNTIFS(Assessment!$B$5:$B$84,$A15,Assessment!$F$5:$F$84,"Not Implemented") -> 0 | G15: =COUNTIFS(Assessment!$B$5:$B$84,$A15,Assessment!$F$5:$F$84,"Not Applicable") -> 0 | H15: =B15-C15 -> 4 | I15: =IF((D15+E15+F15)=0,"",(D15+0.5*E15)/(D15+E15+F15)) | J15: =IFERROR(AVERAGEIFS(Assessment!$G$5:$G$84,Assessment!$B$5:$B$84,$A15),"") | K15: =COUNTIFS(Assessment!$B$5:$B$84,$A15,Assessment!$M$5:$M$84,"P1") -> 0 | L15: =COUNTIFS(Assessment!$B$5:$B$84,$A15,Assessment!$M$5:$M$84,"P2") -> 0
A16: TOTAL | B16: =SUM(B5:B15) -> 80 | C16: =SUM(C5:C15) -> 0 | D16: =SUM(D5:D15) -> 0 | E16: =SUM(E5:E15) -> 0 | F16: =SUM(F5:F15) -> 0 | G16: =SUM(G5:G15) -> 0 | H16: =SUM(H5:H15) -> 80 | I16: =IF((D16+E16+F16)=0,"",(D16+0.5*E16)/(D16+E16+F16)) | J16: =IFERROR(AVERAGE(Assessment!$G$5:$G$84),"") | K16: =SUM(K5:K15) -> 0 | L16: =SUM(L5:L15) -> 0
A18: Coverage % = (Implemented + 0.5 × Partial) ÷ (Implemented + Partial + Not Implemented). Not Applicable and unassessed controls are excluded.

Sheet Checklist
A1: ISACA Secure by Default Checklist (Figure 4) — Rolled Up from Controls
A2: Each item's status is computed from the Assessment controls mapped to it (Secure by Default # column). Use the override column only with a documented reason.
A4: # | B4: Secure by Default item | C4: Linked controls | D4: Mapped | E4: Implemented | F4: Partial | G4: Not Impl. | H4: Coverage % | I4: Computed status | J4: Assessor override | K4: Override rationale / notes
A5: 1 | B5: Inventory all agents, tools, models, memory stores, and providers. | C5: GOV-01 | D5: =COUNTIF(Assessment!$D$5:$D$84,A5) -> 1 | E5: =COUNTIFS(Assessment!$D$5:$D$84,A5,Assessment!$F$5:$F$84,"Implemented") -> 0 | F5: =COUNTIFS(Assessment!$D$5:$D$84,A5,Assessment!$F$5:$F$84,"Partially Implemented") -> 0 | G5: =COUNTIFS(Assessment!$D$5:$D$84,A5,Assessment!$F$5:$F$84,"Not Implemented") -> 0 | H5: =IF((E5+F5+G5)=0,"",(E5+0.5*F5)/(E5+F5+G5)) | I5: =IF(H5="","Not assessed",IF(H5=1,"Met",IF(H5>=0.5,"Partially met","Not met"))) -> Not assessed
A6: 2 | B6: Define trust boundaries and owners. | C6: GOV-02, GOV-03 | D6: =COUNTIF(Assessment!$D$5:$D$84,A6) -> 2 | E6: =COUNTIFS(Assessment!$D$5:$D$84,A6,Assessment!$F$5:$F$84,"Implemented") -> 0 | F6: =COUNTIFS(Assessment!$D$5:$D$84,A6,Assessment!$F$5:$F$84,"Partially Implemented") -> 0 | G6: =COUNTIFS(Assessment!$D$5:$D$84,A6,Assessment!$F$5:$F$84,"Not Implemented") -> 0 | H6: =IF((E6+F6+G6)=0,"",(E6+0.5*F6)/(E6+F6+G6)) | I6: =IF(H6="","Not assessed",IF(H6=1,"Met",IF(H6>=0.5,"Partially met","Not met"))) -> Not assessed
A7: 3 | B7: Use per-agent identity and least privilege. | C7: IAM-01, IAM-04, IAM-05, IAM-07 | D7: =COUNTIF(Assessment!$D$5:$D$84,A7) -> 4 | E7: =COUNTIFS(Assessment!$D$5:$D$84,A7,Assessment!$F$5:$F$84,"Implemented") -> 0 | F7: =COUNTIFS(Assessment!$D$5:$D$84,A7,Assessment!$F$5:$F$84,"Partially Implemented") -> 0 | G7: =COUNTIFS(Assessment!$D$5:$D$84,A7,Assessment!$F$5:$F$84,"Not Implemented") -> 0 | H7: =IF((E7+F7+G7)=0,"",(E7+0.5*F7)/(E7+F7+G7)) | I7: =IF(H7="","Not assessed",IF(H7=1,"Met",IF(H7>=0.5,"Partially met","Not met"))) -> Not assessed
A8: 4 | B8: Prefer short-lived credentials and federated identity. | C8: IAM-02, IAM-03, DAT-02 | D8: =COUNTIF(Assessment!$D$5:$D$84,A8) -> 3 | E8: =COUNTIFS(Assessment!$D$5:$D$84,A8,Assessment!$F$5:$F$84,"Implemented") -> 0 | F8: =COUNTIFS(Assessment!$D$5:$D$84,A8,Assessment!$F$5:$F$84,"Partially Implemented") -> 0 | G8: =COUNTIFS(Assessment!$D$5:$D$84,A8,Assessment!$F$5:$F$84,"Not Implemented") -> 0 | H8: =IF((E8+F8+G8)=0,"",(E8+0.5*F8)/(E8+F8+G8)) | I8: =IF(H8="","Not assessed",IF(H8=1,"Met",IF(H8>=0.5,"Partially met","Not met"))) -> Not assessed
A9: 5 | B9: Employ sandbox execution and segment networks. | C9: SEG-01, SEG-02, SEG-03, SEG-06 | D9: =COUNTIF(Assessment!$D$5:$D$84,A9) -> 4 | E9: =COUNTIFS(Assessment!$D$5:$D$84,A9,Assessment!$F$5:$F$84,"Implemented") -> 0 | F9: =COUNTIFS(Assessment!$D$5:$D$84,A9,Assessment!$F$5:$F$84,"Partially Implemented") -> 0 | G9: =COUNTIFS(Assessment!$D$5:$D$84,A9,Assessment!$F$5:$F$84,"Not Implemented") -> 0 | H9: =IF((E9+F9+G9)=0,"",(E9+0.5*F9)/(E9+F9+G9)) | I9: =IF(H9="","Not assessed",IF(H9=1,"Met",IF(H9>=0.5,"Partially met","Not met"))) -> Not assessed
A10: 6 | B10: Deny outbound access by default. | C10: SEG-04, SEG-05, TAPI-03, TAPI-05 | D10: =COUNTIF(Assessment!$D$5:$D$84,A10) -> 4 | E10: =COUNTIFS(Assessment!$D$5:$D$84,A10,Assessment!$F$5:$F$84,"Implemented") -> 0 | F10: =COUNTIFS(Assessment!$D$5:$D$84,A10,Assessment!$F$5:$F$84,"Partially Implemented") -> 0 | G10: =COUNTIFS(Assessment!$D$5:$D$84,A10,Assessment!$F$5:$F$84,"Not Implemented") -> 0 | H10: =IF((E10+F10+G10)=0,"",(E10+0.5*F10)/(E10+F10+G10)) | I10: =IF(H10="","Not assessed",IF(H10=1,"Met",IF(H10>=0.5,"Partially met","Not met"))) -> Not assessed
A11: 7 | B11: Treat all retrieved content and tool output as untrusted. | C11: PID-01, PID-02, PID-03, PID-04, PID-05, PID-07, DAT-09, TAPI-06 | D11: =COUNTIF(Assessment!$D$5:$D$84,A11) -> 8 | E11: =COUNTIFS(Assessment!$D$5:$D$84,A11,Assessment!$F$5:$F$84,"Implemented") -> 0 | F11: =COUNTIFS(Assessment!$D$5:$D$84,A11,Assessment!$F$5:$F$84,"Partially Implemented") -> 0 | G11: =COUNTIFS(Assessment!$D$5:$D$84,A11,Assessment!$F$5:$F$84,"Not Implemented") -> 0 | H11: =IF((E11+F11+G11)=0,"",(E11+0.5*F11)/(E11+F11+G11)) | I11: =IF(H11="","Not assessed",IF(H11=1,"Met",IF(H11>=0.5,"Partially met","Not met"))) -> Not assessed
A12: 8 | B12: Protect memory with tenant/session isolation and retention controls. | C12: IAM-08, DAT-05, DAT-06, DAT-07, DAT-08 | D12: =COUNTIF(Assessment!$D$5:$D$84,A12) -> 5 | E12: =COUNTIFS(Assessment!$D$5:$D$84,A12,Assessment!$F$5:$F$84,"Implemented") -> 0 | F12: =COUNTIFS(Assessment!$D$5:$D$84,A12,Assessment!$F$5:$F$84,"Partially Implemented") -> 0 | G12: =COUNTIFS(Assessment!$D$5:$D$84,A12,Assessment!$F$5:$F$84,"Not Implemented") -> 0 | H12: =IF((E12+F12+G12)=0,"",(E12+0.5*F12)/(E12+F12+G12)) | I12: =IF(H12="","Not assessed",IF(H12=1,"Met",IF(H12>=0.5,"Partially met","Not met"))) -> Not assessed
A13: 9 | B13: Put all tool actions behind a policy enforcement point. | C13: SDL-04, SEG-07, PID-06, TAPI-01, TAPI-02, TAPI-04, POL-01, POL-02 | D13: =COUNTIF(Assessment!$D$5:$D$84,A13) -> 8 | E13: =COUNTIFS(Assessment!$D$5:$D$84,A13,Assessment!$F$5:$F$84,"Implemented") -> 0 | F13: =COUNTIFS(Assessment!$D$5:$D$84,A13,Assessment!$F$5:$F$84,"Partially Implemented") -> 0 | G13: =COUNTIFS(Assessment!$D$5:$D$84,A13,Assessment!$F$5:$F$84,"Not Implemented") -> 0 | H13: =IF((E13+F13+G13)=0,"",(E13+0.5*F13)/(E13+F13+G13)) | I13: =IF(H13="","Not assessed",IF(H13=1,"Met",IF(H13>=0.5,"Partially met","Not met"))) -> Not assessed
A14: 10 | B14: Require human approval for high-risk actions. | C14: POL-03, POL-04, POL-05 | D14: =COUNTIF(Assessment!$D$5:$D$84,A14) -> 3 | E14: =COUNTIFS(Assessment!$D$5:$D$84,A14,Assessment!$F$5:$F$84,"Implemented") -> 0 | F14: =COUNTIFS(Assessment!$D$5:$D$84,A14,Assessment!$F$5:$F$84,"Partially Implemented") -> 0 | G14: =COUNTIFS(Assessment!$D$5:$D$84,A14,Assessment!$F$5:$F$84,"Not Implemented") -> 0 | H14: =IF((E14+F14+G14)=0,"",(E14+0.5*F14)/(E14+F14+G14)) | I14: =IF(H14="","Not assessed",IF(H14=1,"Met",IF(H14>=0.5,"Partially met","Not met"))) -> Not assessed
A15: 11 | B15: Log prompts, tool calls, decisions, and approvals with redaction. | C15: SDL-12, DAT-04, MON-01, MON-02, MON-03 | D15: =COUNTIF(Assessment!$D$5:$D$84,A15) -> 5 | E15: =COUNTIFS(Assessment!$D$5:$D$84,A15,Assessment!$F$5:$F$84,"Implemented") -> 0 | F15: =COUNTIFS(Assessment!$D$5:$D$84,A15,Assessment!$F$5:$F$84,"Partially Implemented") -> 0 | G15: =COUNTIFS(Assessment!$D$5:$D$84,A15,Assessment!$F$5:$F$84,"Not Implemented") -> 0 | H15: =IF((E15+F15+G15)=0,"",(E15+0.5*F15)/(E15+F15+G15)) | I15: =IF(H15="","Not assessed",IF(H15=1,"Met",IF(H15>=0.5,"Partially met","Not met"))) -> Not assessed
A16: 12 | B16: Pin models and dependencies; use SBOMs and signing. | C16: SDL-14, SUP-01, SUP-02 | D16: =COUNTIF(Assessment!$D$5:$D$84,A16) -> 3 | E16: =COUNTIFS(Assessment!$D$5:$D$84,A16,Assessment!$F$5:$F$84,"Implemented") -> 0 | F16: =COUNTIFS(Assessment!$D$5:$D$84,A16,Assessment!$F$5:$F$84,"Partially Implemented") -> 0 | G16: =COUNTIFS(Assessment!$D$5:$D$84,A16,Assessment!$F$5:$F$84,"Not Implemented") -> 0 | H16: =IF((E16+F16+G16)=0,"",(E16+0.5*F16)/(E16+F16+G16)) | I16: =IF(H16="","Not assessed",IF(H16=1,"Met",IF(H16>=0.5,"Partially met","Not met"))) -> Not assessed
... A19: 15 | B19: Add kill switches, rollback capability, and safe-mode operations. | C19: SDL-15, POL-06, MON-05, SUP-07, RES-02, RES-03, RES-04 | D19: =COUNTIF(Assessment!$D$5:$D$84,A19) -> 7 | E19: =COUNTIFS(Assessment!$D$5:$D$84,A19,Assessment!$F$5:$F$84,"Implemented") -> 0 | F19: =COUNTIFS(Assessment!$D$5:$D$84,A19,Assessment!$F$5:$F$84,"Partially Implemented") -> 0 | G19: =COUNTIFS(Assessment!$D$5:$D$84,A19,Assessment!$F$5:$F$84,"Not Implemented") -> 0 | H19: =IF((E19+F19+G19)=0,"",(E19+0.5*F19)/(E19+F19+G19)) | I19: =IF(H19="","Not assessed",IF(H19=1,"Met",IF(H19>=0.5,"Partially met","Not met"))) -> Not assessed
A21: Items met | C21: =COUNTIF(I5:I19,"Met")&" of "&(15-COUNTIF(I5:I19,"Not assessed"))&" assessed items" -> 0 of 0 assessed items
A22: Thresholds: Met = 100% coverage of mapped controls; Partially met = 50–99%; Not met = below 50%.

Sheet Data Handling
A1: Agent Data Handling Decisions (ISACA Appendix A, Figure 5)
A2: Decide what each data class may do inside the agent. Yellow columns are decisions. Columns A–C summarize ISACA; columns E–J are a suggested starting baseline added for this worksheet. Supports DAT-03 and SDL-10.
A4: Data class | B4: Examples (ISACA) | C4: Baseline handling (ISACA: store / send / access / keep / dispose) | D4: Agents in scope that touch this class | E4: Agent may access? | F4: In prompts / context? | G4: In persistent memory? | H4: In logs / traces? | I4: Sent to external model provider? | J4: Suggested agent-specific controls | K4: Current state | L4: Gap / action
A5: Public | B5: Public website content, press releases, published brochures, approved job postings | C5: Store in approved business systems; protect from unauthorized changes. Send through normal business and public channels. Public to access; limit edit access. Keep as useful for business, archival, or legal needs. Normal disposal. | E5: Yes | F5: Yes | G5: Yes | H5: Yes | I5: Yes | J5: Agents may read freely, but content fetched from the open web is still untrusted input (PID-01). Agents should not publish or edit public content without approval (POL-03).
A6: Internal | B6: Internal procedures, org charts, team documents, routine internal email, meeting notes | C6: Store in approved company systems only; avoid personal or unapproved cloud storage. Send through approved company email, chat, and collaboration tools. Employees and approved third parties with business need. Per business retention schedule. Standard deletion. | E6: Conditional | F6: Yes | G6: Conditional | H6: Yes | I6: Conditional | J6: Restrict to agents with a business need; approved model providers under contract only (SUP-05); memory TTL aligned to the retention schedule (DAT-06); no forwarding to unapproved destinations (SEG-04).
A7: Confidential | B7: Customer records, employee records, contracts, financial reports, nonpublic strategy documents, most personal data | C7: Store in approved managed systems; encryption at rest required. Send via approved secure methods, encrypted in transit, recipients verified. Authorized users only, role-based, logged and reviewed. Per documented retention schedule. Secure deletion; approved shredding and secure wipe. | E7: Conditional | F7: Conditional | G7: Conditional | H7: Redacted only | I7: Conditional | J7: Authorization check on every retrieval and memory read (IAM-08, DAT-07); per-tenant/user memory isolation (DAT-05); provider contract covers training use, retention, residency, breach notice (SUP-05); redact in logs (DAT-04); outbound actions carrying this data pass the PEP (POL-01).
A8: Restricted / Highly sensitive | B8: Health data, special category personal data, government ID numbers, payment data, passwords, cryptographic keys, M&A data, security investigation files | C8: Store only in explicitly approved, tightly controlled systems; strong encryption required. Send via approved secure transfer only; recipient identity and authorization confirmed. Strict need-to-know, formal approval, MFA, tightly controlled privileged access. Shortest justified retention. Verified secure destruction. | E8: No | F8: No | G8: No | H8: No | I8: No | J8: Default deny. Passwords and keys never enter prompts (DAT-01). If a use case is approved by exception: tokenize or redact before inference, dedicated approved endpoint, no persistent memory, HITL approval for any action that transmits or changes this data (POL-03), privileged access review of logs. Regulated data (e.g., PHI, PCI) carries further obligations beyond this guide.
A10: Values in columns E–I are a suggested starting position, not ISACA requirements. Replace them with the decisions approved by the data owner, and document the conditions for any 'Conditional' entry in Current state.

Sheet Lists
A1: Implemented | B1: 0 | C1: High | E1: Met
A2: Partially Implemented | B2: 1 | C2: Medium | E2: Partially met
A3: Not Implemented | B3: 2 | C3: Low | E3: Not met
A4: Not Applicable | B4: 3 | E4: Not applicable
B5: 4
B6: 5
